streamnet/__init__.py
streamnet/io.py
streamnet/node.py
streamnet/streamnet.py
streamnet/utils.py
streamnet-0.1.0.dist-info/LICENSE.md
streamnet-0.1.0.dist-info/METADATA
streamnet-0.1.0.dist-info/WHEEL
streamnet-0.1.0.dist-info/top_level.txt
streamnet-0.1.0.dist-info/RECORD
