Metadata-Version: 2.1
Name: streamnet
Version: 0.1.0
Summary: A directed netlist representation for stream processing
Author: Angel Yanguas-Gil
Project-URL: Homepage, https://github.com/spikelearn/streamnet
Keywords: netlist,graphs,networks,programming models
Classifier: Programming Language :: Python :: 3
Classifier: License :: OSI Approved :: BSD License
Classifier: Operating System :: OS Independent
License-File: LICENSE.md
Requires-Dist: numpy
